{
    "name": "GTK::Simple",
    "description": "Simple GTK 3 binding using NativeCall",
    "version": "0.3.2",
    "authors": [
        "Jonathan Worthington",
        "Moritz Lenz",
        "Timo Paulssen",
        "Ahmad M. Zawawi",
        "Jonathan Stowe",
        "ab5tract",
        "momozor",
        "Zoffix Znet",
        "Nick Logan",
        "finanalyst aka Richard Hainsworth"
    ],
    "auth": "zef:finanalyst",
    "depends": {
        "by-kernel.name": {
            "macos": "MacOS::NativeLib:ver<0.0.5>:auth<zef:lizmat>",
            "": ""
        }
    },
    "test-depends": [
        "Test"
    ],
    "provides": {
        "GTK::Simple": "lib/GTK/Simple.rakumod",
        "GTK::Simple::ActionBar": "lib/GTK/Simple/ActionBar.rakumod",
        "GTK::Simple::App": "lib/GTK/Simple/App.rakumod",
        "GTK::Simple::Box": "lib/GTK/Simple/Box.rakumod",
        "GTK::Simple::Button": "lib/GTK/Simple/Button.rakumod",
        "GTK::Simple::Calendar": "lib/GTK/Simple/Calendar.rakumod",
        "GTK::Simple::CheckButton": "lib/GTK/Simple/CheckButton.rakumod",
        "GTK::Simple::CheckMenuItem": "lib/GTK/Simple/CheckMenuItem.rakumod",
        "GTK::Simple::ComboBoxText": "lib/GTK/Simple/ComboBoxText.rakumod",
        "GTK::Simple::Common": "lib/GTK/Simple/Common.rakumod",
        "GTK::Simple::ConnectionHandler": "lib/GTK/Simple/ConnectionHandler.rakumod",
        "GTK::Simple::Container": "lib/GTK/Simple/Container.rakumod",
        "GTK::Simple::DrawingArea": "lib/GTK/Simple/DrawingArea.rakumod",
        "GTK::Simple::Entry": "lib/GTK/Simple/Entry.rakumod",
        "GTK::Simple::FileChooserButton": "lib/GTK/Simple/FileChooserButton.rakumod",
        "GTK::Simple::Frame": "lib/GTK/Simple/Frame.rakumod",
        "GTK::Simple::GDK": "lib/GTK/Simple/GDK.rakumod",
        "GTK::Simple::Grid": "lib/GTK/Simple/Grid.rakumod",
        "GTK::Simple::HBox": "lib/GTK/Simple/HBox.rakumod",
        "GTK::Simple::Image": "lib/GTK/Simple/Image.rakumod",
        "GTK::Simple::Label": "lib/GTK/Simple/Label.rakumod",
        "GTK::Simple::LevelBar": "lib/GTK/Simple/LevelBar.rakumod",
        "GTK::Simple::LinkButton": "lib/GTK/Simple/LinkButton.rakumod",
        "GTK::Simple::ListBox": "lib/GTK/Simple/ListBox.rakumod",
        "GTK::Simple::MarkUpLabel": "lib/GTK/Simple/MarkUpLabel.rakumod",
        "GTK::Simple::Menu": "lib/GTK/Simple/Menu.rakumod",
        "GTK::Simple::MenuBar": "lib/GTK/Simple/MenuBar.rakumod",
        "GTK::Simple::MenuItem": "lib/GTK/Simple/MenuItem.rakumod",
        "GTK::Simple::MenuToolButton": "lib/GTK/Simple/MenuToolButton.rakumod",
        "GTK::Simple::NativeLib": "lib/GTK/Simple/NativeLib.rakumod",
        "GTK::Simple::PlacesSidebar": "lib/GTK/Simple/PlacesSidebar.rakumod",
        "GTK::Simple::ProgressBar": "lib/GTK/Simple/ProgressBar.rakumod",
        "GTK::Simple::PropertyFacade": "lib/GTK/Simple/PropertyFacade.rakumod",
        "GTK::Simple::RadioButton": "lib/GTK/Simple/RadioButton.rakumod",
        "GTK::Simple::Raw": "lib/GTK/Simple/Raw.rakumod",
        "GTK::Simple::Scale": "lib/GTK/Simple/Scale.rakumod",
        "GTK::Simple::Scheduler": "lib/GTK/Simple/Scheduler.rakumod",
        "GTK::Simple::ScrolledWindow": "lib/GTK/Simple/ScrolledWindow.rakumod",
        "GTK::Simple::Separator": "lib/GTK/Simple/Separator.rakumod",
        "GTK::Simple::Spinner": "lib/GTK/Simple/Spinner.rakumod",
        "GTK::Simple::StatusBar": "lib/GTK/Simple/StatusBar.rakumod",
        "GTK::Simple::Switch": "lib/GTK/Simple/Switch.rakumod",
        "GTK::Simple::TextView": "lib/GTK/Simple/TextView.rakumod",
        "GTK::Simple::ToggleButton": "lib/GTK/Simple/ToggleButton.rakumod",
        "GTK::Simple::Toolbar": "lib/GTK/Simple/Toolbar.rakumod",
        "GTK::Simple::VBox": "lib/GTK/Simple/VBox.rakumod",
        "GTK::Simple::Widget": "lib/GTK/Simple/Widget.rakumod",
        "GTK::Simple::Window": "lib/GTK/Simple/Window.rakumod",
        "GTK::Simple::Distro::Resources": "lib/GTK/Simple/Distro/Resources.rakumod"
    },
    "resources": [
        "camelia-logo.png"
    ],
    "support": {
        "email": "rnhainsworth@gmail.com",
        "bugtracker": "https://github.com/finanalyst/GTK-Simple/issues",
        "source": "https://github.com/finanalyst/GTK-Simple.git"
    },
    "license": "Artistic-2.0",
    "tags": [
        "gui"
    ],
    "source-url": "git://github.com/finanalyst/GTK-Simple.git"
}